LICENSE
setup.py
labbu/__init__.py
labbu/labbu.py
labbu.egg-info/PKG-INFO
labbu.egg-info/SOURCES.txt
labbu.egg-info/dependency_links.txt
labbu.egg-info/top_level.txt
labbu/modules/__init__.py
labbu/modules/label.py